artifacts_keyring-1.0.0.dist-info/RECORD
artifacts_keyring-1.0.0.dist-info/WHEEL
artifacts_keyring-1.0.0.dist-info/entry_points.txt
artifacts_keyring-1.0.0.dist-info/top_level.txt
artifacts_keyring-1.0.0.dist-info/METADATA
artifacts_keyring-1.0.0.dist-info/licenses/LICENSE.txt
tests/test_backend.py
tests/__init__.py
artifacts_keyring/support.py
artifacts_keyring/__init__.py
artifacts_keyring/plugin.py
artifacts_keyring/plugins/ThirdPartyNotices.txt
artifacts_keyring/plugins/LICENSE
artifacts_keyring/plugins/EULA_Microsoft Visual Studio Team Services Credential Provider.docx
artifacts_keyring/plugins/plugins/netcore/CredentialProvider.Microsoft/Microsoft.CSharp.dll
artifacts_keyring/plugins/plugins/netcore/CredentialProvider.Microsoft/System.Web.dll
artifacts_keyring/plugins/plugins/netcore/CredentialProvider.Microsoft/System.Diagnostics.Contracts.dll
artifacts_keyring/plugins/plugins/netcore/CredentialProvider.Microsoft/System.ServiceModel.Web.dll
artifacts_keyring/plugins/plugins/netcore/CredentialProvider.Microsoft/System.Diagnostics.FileVersionInfo.dll
artifacts_keyring/plugins/plugins/netcore/CredentialProvider.Microsoft/System.Runtime.Intrinsics.dll
artifacts_keyring/plugins/plugins/netcore/CredentialProvider.Microsoft/System.Net.Security.dll
artifacts_keyring/plugins/plugins/netcore/CredentialProvider.Microsoft/System.Xml.XPath.XDocument.dll
artifacts_keyring/plugins/plugins/netcore/CredentialProvider.Microsoft/System.Xml.Linq.dll
artifacts_keyring/plugins/plugins/netcore/CredentialProvider.Microsoft/System.Net.WebSockets.Client.dll
artifacts_keyring/plugins/plugins/netcore/CredentialProvider.Microsoft/createdump
artifacts_keyring/plugins/plugins/netcore/CredentialProvider.Microsoft/System.IO.dll
artifacts_keyring/plugins/plugins/netcore/CredentialProvider.Microsoft/CredentialProvider.Microsoft.deps.json
artifacts_keyring/plugins/plugins/netcore/CredentialProvider.Microsoft/System.Dynamic.Runtime.dll
artifacts_keyring/plugins/plugins/netcore/CredentialProvider.Microsoft/System.Runtime.Serialization.Xml.dll
artifacts_keyring/plugins/plugins/netcore/CredentialProvider.Microsoft/CredentialProvider.Microsoft.pdb
artifacts_keyring/plugins/plugins/netcore/CredentialProvider.Microsoft/System.Security.Principal.dll
