Metadata-Version: 2.4
Name: artifacts-keyring
Version: 1.0.0
Summary: "Automatically retrieve credentials for Azure Artifacts."
Home-page: https://github.com/Microsoft/artifacts-keyring
Author: Microsoft Corporation
License: "MIT"
Classifier: Development Status :: 3 - Alpha
Classifier: Intended Audience :: Developers
Classifier: Programming Language :: Python :: 3.9
Classifier: Programming Language :: Python :: 3.10
Classifier: Programming Language :: Python :: 3.11
Classifier: Programming Language :: Python :: 3.12
Classifier: Programming Language :: Python :: 3.13
Classifier: Operating System :: Microsoft :: Windows
Classifier: Operating System :: POSIX :: Linux
Classifier: Operating System :: MacOS :: MacOS X
Requires-Python: >=3.9
License-File: LICENSE.txt
Requires-Dist: keyring>=22.0
Requires-Dist: requests>=2.20.0
Dynamic: license-file
